soda_update_version/__main__.py
soda_update_version/args.py
soda_update_version/main.py
soda_update_version/steps.py
soda_update_version/toml.py
soda_update_version/version.py
soda_update_version-2025.11.7.0.dist-info/METADATA
soda_update_version-2025.11.7.0.dist-info/WHEEL
soda_update_version-2025.11.7.0.dist-info/entry_points.txt
soda_update_version-2025.11.7.0.dist-info/licenses/LICENSE
soda_update_version-2025.11.7.0.dist-info/RECORD
