Metadata-Version: 2.4
Name: soda-update-version
Version: 2025.11.7.0
Summary: update version using datetime format for python projects
Project-URL: Repository, https://github.com/soda92/update-version
License-File: LICENSE
Requires-Python: >=3.8
Requires-Dist: tomli>=2.3.0
Requires-Dist: twine>=6.1.0
